CHANGELOG.rst
MANIFEST.in
README.rst
setup.py
echarts_china_provinces_pypkg/__init__.py
echarts_china_provinces_pypkg/_version.py
echarts_china_provinces_pypkg.egg-info/PKG-INFO
echarts_china_provinces_pypkg.egg-info/SOURCES.txt
echarts_china_provinces_pypkg.egg-info/dependency_links.txt
echarts_china_provinces_pypkg.egg-info/not-zip-safe
echarts_china_provinces_pypkg.egg-info/requires.txt
echarts_china_provinces_pypkg.egg-info/top_level.txt
echarts_china_provinces_pypkg/resources/registry.json
echarts_china_provinces_pypkg/resources/echarts-china-provinces-js/anhui.js
echarts_china_provinces_pypkg/resources/echarts-china-provinces-js/fujian.js
echarts_china_provinces_pypkg/resources/echarts-china-provinces-js/gansu.js
echarts_china_provinces_pypkg/resources/echarts-china-provinces-js/guangdong.js
echarts_china_provinces_pypkg/resources/echarts-china-provinces-js/guangxi.js
echarts_china_provinces_pypkg/resources/echarts-china-provinces-js/guizhou.js
echarts_china_provinces_pypkg/resources/echarts-china-provinces-js/hainan.js
echarts_china_provinces_pypkg/resources/echarts-china-provinces-js/hebei.js
echarts_china_provinces_pypkg/resources/echarts-china-provinces-js/heilongjiang.js
echarts_china_provinces_pypkg/resources/echarts-china-provinces-js/henan.js
echarts_china_provinces_pypkg/resources/echarts-china-provinces-js/hubei.js
echarts_china_provinces_pypkg/resources/echarts-china-provinces-js/hunan.js
echarts_china_provinces_pypkg/resources/echarts-china-provinces-js/jiangsu.js
echarts_china_provinces_pypkg/resources/echarts-china-provinces-js/jiangxi.js
echarts_china_provinces_pypkg/resources/echarts-china-provinces-js/jilin.js
echarts_china_provinces_pypkg/resources/echarts-china-provinces-js/liaoning.js
echarts_china_provinces_pypkg/resources/echarts-china-provinces-js/main.js
echarts_china_provinces_pypkg/resources/echarts-china-provinces-js/neimenggu.js
echarts_china_provinces_pypkg/resources/echarts-china-provinces-js/ningxia.js
echarts_china_provinces_pypkg/resources/echarts-china-provinces-js/qinghai.js
echarts_china_provinces_pypkg/resources/echarts-china-provinces-js/shandong.js
echarts_china_provinces_pypkg/resources/echarts-china-provinces-js/shanxi.js
echarts_china_provinces_pypkg/resources/echarts-china-provinces-js/shanxi1.js
